modrl/__init__.py
modrl/agents/classical/n-offp-sarsa.py
modrl/agents/classical/n-tree.py
modrl/agents/classical/offp-monte-carlo.py
modrl/agents/classical/onp-monte-carlo.py
modrl/agents/classical/td-doubleq.py
modrl/agents/classical/td-q.py
modrl/agents/classical/td-sarsa.py
modrl/agents/deep/dqn.py
modrl/agents/deep/ppo.py
modrl/agents/deep/semi-gradient-sarsa.py
modrl/agents/deep/vpg.py
modrl/bandits/__init__.py
modrl/bandits/classical/__init__.py
modrl/bandits/classical/egreedy.py
modrl/bandits/classical/exp3.py
modrl/bandits/classical/gradient.py
modrl/bandits/classical/ts.py
modrl/bandits/classical/ucb.py
modrl/bandits/contextual/linucb.py
modrl/evaluation/__init__.py
modrl/evaluation/cum-rew.py
modrl/evaluation/regret.py
modrl/nn/cnn.py
modrl/nn/mlp.py
modrl/policies/esoft.py
modrl/policies/softmax.py
modrl/utils/epsilon-scheduler.py
modrl/utils/replay-buffer.py
modrl-0.0.2.dist-info/METADATA
modrl-0.0.2.dist-info/WHEEL
modrl-0.0.2.dist-info/top_level.txt
modrl-0.0.2.dist-info/RECORD
