Metadata-Version: 2.4
Name: modrl
Version: 0.0.2
Summary: A Python package for modular implementation of classical and deep Reinforcement Learning algorithms.
Author-email: Tyler Wallett <twallett@gwu.edu>
Project-URL: Homepage, https://github.com/twallett/modrl
Project-URL: Repository, https://github.com/twallett/modrl
Classifier: Programming Language :: Python :: 3
Classifier: Programming Language :: Python :: 3.8
Classifier: Programming Language :: Python :: 3.9
Classifier: Programming Language :: Python :: 3.10
Classifier: Programming Language :: Python :: 3.11
Classifier: License :: OSI Approved :: MIT License
Classifier: Operating System :: OS Independent
Classifier: Intended Audience :: Science/Research
Classifier: Topic :: Scientific/Engineering :: Artificial Intelligence
Requires-Python: >=3.8
Requires-Dist: numpy
